Metadata-Version: 2.1
Name: discum
Version: 1.4.1
Summary: A Discord API Wrapper for Userbots/Selfbots written in Python.
Home-page: https://github.com/Merubokkusu/Discord-S.C.U.M
Author: Merubokkusu
Author-email: loser@merubokkusu.com
License: MIT
Platform: UNKNOWN
Classifier: License :: OSI Approved :: MIT License
Classifier: Programming Language :: Python
Classifier: Programming Language :: Python :: 2
Classifier: Programming Language :: Python :: 2.7
Classifier: Programming Language :: Python :: 3
Classifier: Programming Language :: Python :: 3.5
Classifier: Programming Language :: Python :: 3.6
Classifier: Programming Language :: Python :: 3.7
Classifier: Programming Language :: Python :: 3.8
Classifier: Programming Language :: Python :: Implementation :: CPython
Classifier: Programming Language :: Python :: Implementation :: PyPy
Requires-Python: >=2.7.0
Provides-Extra: ra
